kanka/__init__.py
kanka/_version.py
kanka/client.py
kanka/exceptions.py
kanka/managers.py
kanka/py.typed
kanka/types.py
kanka/models/__init__.py
kanka/models/base.py
kanka/models/common.py
kanka/models/entities.py
python_kanka-2.2.0.dist-info/licenses/LICENSE
python_kanka-2.2.0.dist-info/METADATA
python_kanka-2.2.0.dist-info/WHEEL
python_kanka-2.2.0.dist-info/top_level.txt
python_kanka-2.2.0.dist-info/RECORD
