Metadata-Version: 2.4
Name: python-kanka
Version: 2.2.0
Summary: A modern Python client for the Kanka API with full typing support
Home-page: https://github.com/ervwalter/python-kanka
Author: Erv Walter
Author-email: erv@ewal.net
License: MIT
Project-URL: Bug Reports, https://github.com/ervwalter/python-kanka/issues
Project-URL: Source, https://github.com/ervwalter/python-kanka
Project-URL: Documentation, https://github.com/ervwalter/python-kanka#readme
Project-URL: Kanka API, https://kanka.io/en-US/docs/1.0
Keywords: kanka api client worldbuilding rpg campaign tabletop ttrpg dnd pathfinder
Classifier: Development Status :: 4 - Beta
Classifier: Intended Audience :: Developers
Classifier: Topic :: Games/Entertainment :: Role-Playing
Classifier: Topic :: Software Development :: Libraries :: Python Modules
Classifier: License :: OSI Approved :: MIT License
Classifier: Programming Language :: Python :: 3
Classifier: Programming Language :: Python :: 3.9
Classifier: Programming Language :: Python :: 3.10
Classifier: Programming Language :: Python :: 3.11
Classifier: Programming Language :: Python :: 3.12
Classifier: Operating System :: OS Independent
Classifier: Typing :: Typed
Requires-Python: >=3.9
License-File: LICENSE
Requires-Dist: requests==2.32.4
Requires-Dist: requests_toolbelt>=0.9.1
Requires-Dist: pydantic==2.11.5
Provides-Extra: dev
Requires-Dist: pytest>=7.0.0; extra == "dev"
Requires-Dist: pytest-cov>=4.0.0; extra == "dev"
Requires-Dist: pytest-mock>=3.10.0; extra == "dev"
Requires-Dist: black>=23.0.0; extra == "dev"
Requires-Dist: isort>=5.12.0; extra == "dev"
Requires-Dist: ruff>=0.1.0; extra == "dev"
Requires-Dist: mypy>=1.0.0; extra == "dev"
Requires-Dist: pre-commit>=3.0.0; extra == "dev"
Dynamic: author
Dynamic: author-email
Dynamic: classifier
Dynamic: description
Dynamic: description-content-type
Dynamic: home-page
Dynamic: keywords
Dynamic: license
Dynamic: license-file
Dynamic: project-url
Dynamic: provides-extra
Dynamic: requires-dist
Dynamic: requires-python
Dynamic: summary
